pyfrigg/__init__.py
pyfrigg/elasticsearch.py
pyfrigg/mysql.py
pyfrigg/requests.py
pyfrigg-0.4.0.dist-info/LICENSE.txt
pyfrigg-0.4.0.dist-info/METADATA
pyfrigg-0.4.0.dist-info/WHEEL
pyfrigg-0.4.0.dist-info/top_level.txt
pyfrigg-0.4.0.dist-info/RECORD
