Metadata-Version: 2.1
Name: pyfrigg
Version: 0.4.0
Summary: High level data loading utils
Home-page: https://bitbucket.org/Vnk260957/pyfrigg.git
Author: Nick Kuzmenkov
Author-email: nickuzmenkov@yahoo.com
License: MIT
Keywords: data,Elasticsearch,MySQL,requests
Platform: UNKNOWN
Classifier: Development Status :: 5 - Production/Stable
Classifier: Intended Audience :: Developers
Classifier: License :: OSI Approved :: MIT License
Classifier: Programming Language :: Python :: 3
Requires-Dist: aiohttp (>=3.7.4)
Requires-Dist: tqdm (>=4.62.0)
Requires-Dist: pandas (>=1.3.0)
Requires-Dist: elasticsearch (>=7.13.3)
Requires-Dist: mysql-connector-python (>=8.0.25)
